pbsmmapi/__init__.py
pbsmmapi/abstract/__init__.py
pbsmmapi/abstract/admin.py
pbsmmapi/abstract/helpers.py
pbsmmapi/abstract/models.py
pbsmmapi/api/__init__.py
pbsmmapi/api/api.py
pbsmmapi/api/helpers.py
pbsmmapi/asset/__init__.py
pbsmmapi/asset/admin.py
pbsmmapi/asset/apps.py
pbsmmapi/asset/helpers.py
pbsmmapi/asset/models.py
pbsmmapi/asset/tasks.py
pbsmmapi/asset/migrations/0001_initial.py
pbsmmapi/asset/migrations/0002_move_assets_data.py
pbsmmapi/asset/migrations/0003_remove_asset_images_json.py
pbsmmapi/asset/migrations/0004_alter_asset_date_last_api_update.py
pbsmmapi/asset/migrations/0005_remove_asset_object_type_asset_asset_type.py
pbsmmapi/asset/migrations/0006_asset_franchise.py
pbsmmapi/asset/migrations/0007_alter_asset_id.py
pbsmmapi/asset/migrations/0008_remove_asset_windows_alter_asset_availability_and_more.py
pbsmmapi/asset/migrations/0009_alter_asset_options.py
pbsmmapi/asset/migrations/__init__.py
pbsmmapi/changelog/__init__.py
pbsmmapi/changelog/apps.py
pbsmmapi/changelog/models.py
pbsmmapi/changelog/tasks.py
pbsmmapi/changelog/migrations/0001_initial.py
pbsmmapi/changelog/migrations/__init__.py
pbsmmapi/episode/__init__.py
pbsmmapi/episode/admin.py
pbsmmapi/episode/apps.py
pbsmmapi/episode/forms.py
pbsmmapi/episode/models.py
pbsmmapi/episode/migrations/0001_initial.py
pbsmmapi/episode/migrations/0002_auto_20190430_1853.py
pbsmmapi/episode/migrations/0003_auto_20190430_1926.py
pbsmmapi/episode/migrations/0004_auto_20190430_1949.py
pbsmmapi/episode/migrations/0005_remove_pbsmmepisode_live_as_of_and_more.py
pbsmmapi/episode/migrations/0006_remove_pbsmmepisodeasset_override_default_asset.py
pbsmmapi/episode/migrations/0007_remove_pbsmmepisode_canonical_image_type_override_and_more.py
pbsmmapi/episode/migrations/0008_remove_pbsmmepisodeasset_canonical_image_type_override.py
pbsmmapi/episode/migrations/0009_alter_pbsmmepisode_funder_message_and_more.py
pbsmmapi/episode/migrations/0010_pbsmmepisodeasset_images_json.py
django_pbsmmapi-1.3.4.dist-info/METADATA
django_pbsmmapi-1.3.4.dist-info/WHEEL
django_pbsmmapi-1.3.4.dist-info/licenses/LICENSE
django_pbsmmapi-1.3.4.dist-info/RECORD
