Metadata-Version: 2.4
Name: django-pbsmmapi
Version: 1.3.4
Summary: Django models that import content from the PBS MediaManager API
Author: Bob Donahue
License-Expression: MIT
License-File: LICENSE
Classifier: Development Status :: 5 - Production/Stable
Classifier: Environment :: Web Environment
Classifier: Framework :: Django
Classifier: Framework :: Django :: 4.0
Classifier: Framework :: Django :: 4.1
Classifier: Framework :: Django :: 4.2
Classifier: Framework :: Django :: 5.0
Classifier: Framework :: Django :: 5.1
Classifier: Framework :: Django :: 5.2
Classifier: Intended Audience :: Developers
Classifier: License :: OSI Approved :: MIT License
Classifier: Natural Language :: English
Classifier: Operating System :: OS Independent
Classifier: Topic :: Internet :: WWW/HTTP
Classifier: Topic :: Internet :: WWW/HTTP :: Dynamic Content
Requires-Python: <4.0,>=3.10
Requires-Dist: django>=4.0
Requires-Dist: huey>=2.5.3
Requires-Dist: nltk>=3.9
Requires-Dist: pycaption>=2.2.16
Requires-Dist: python-dateutil
Requires-Dist: pytz
Requires-Dist: requests
